envclasses/__init__.py
envclasses/py.typed
envclasses-0.3.1.dist-info/LICENSE
envclasses-0.3.1.dist-info/WHEEL
envclasses-0.3.1.dist-info/METADATA
envclasses-0.3.1.dist-info/RECORD
