Metadata-Version: 2.1
Name: envclasses
Version: 0.3.1
Summary: envclasses is a library to map fields on dataclass object to environment variables
Home-page: https://yukinarit.github.io/envclasses/envclasses.html
License: MIT
Author: Yukinari Tani
Author-email: yukinarit84@gmail.com
Requires-Python: >=3.6,<4.0
Classifier: Development Status :: 5 - Production/Stable
Classifier: Intended Audience :: Developers
Classifier: License :: OSI Approved :: MIT License
Classifier: Programming Language :: Python :: 3
Classifier: Programming Language :: Python :: 3.10
Classifier: Programming Language :: Python :: 3.6
Classifier: Programming Language :: Python :: 3.7
Classifier: Programming Language :: Python :: 3.8
Classifier: Programming Language :: Python :: 3.9
Classifier: Programming Language :: Python :: Implementation :: CPython
Requires-Dist: dataclasses; python_version < "3.7"
Requires-Dist: pyyaml
Requires-Dist: typing-extensions; python_version < "3.8"
Requires-Dist: typing_inspect (>=0.4.0)
Project-URL: Repository, https://github.com/yukinarit/envclasses
